{
  "ignorePatterns": [
    {
      "pattern": "^http://localhost"
    },
    {
      "pattern": "^http://127.0.0.1"
    },
    {
      "pattern": "^https://github.com/.*/blob/"
    },
    {
      "pattern": "^https://arxiv.org"
    },
    {
      "pattern": "^https://twitter.com/.*"
    },
    {
      "pattern": "^https://x.com/.*"
    },
    {
      "pattern": "^https://wendellhua.github.io/AI-Learning-Roadmap/.*"
    }


  ],
  "timeout": "30s",
  "retryOn429": true,
  "retryCount": 5,
  "fallbackRetryDelay": "30s",
  "aliveStatusCodes": [200, 206, 301, 302, 403]
}
